sadam/__init__.py
sadam/sadam.py
sadam-0.0.1.dist-info/LICENSE
sadam-0.0.1.dist-info/METADATA
sadam-0.0.1.dist-info/WHEEL
sadam-0.0.1.dist-info/top_level.txt
sadam-0.0.1.dist-info/RECORD
