Metadata-Version: 2.1
Name: sadam
Version: 0.0.1
Summary: Scalable Adam Optimizer
Home-page: https://github.com/072jiajia/sadam
Author: Jijia Wu
Author-email: jijiawu.cs@gmail.com
License: MIT
Platform: UNKNOWN
Classifier: License :: OSI Approved :: MIT License
Classifier: Programming Language :: Python :: 3
License-File: LICENSE
